classic/actors/__init__.py
classic/actors/actor.py
classic/actors/supervisor.py
classic_actors-0.3.0.dist-info/licenses/LICENSE
classic_actors-0.3.0.dist-info/METADATA
classic_actors-0.3.0.dist-info/WHEEL
classic_actors-0.3.0.dist-info/top_level.txt
classic_actors-0.3.0.dist-info/RECORD
